pyobfus/__init__.py
pyobfus/cli.py
pyobfus/config.py
pyobfus/config_templates.py
pyobfus/config_validator.py
pyobfus/constants.py
pyobfus/exceptions.py
pyobfus/trial.py
pyobfus/trial_cli.py
pyobfus/utils.py
pyobfus/core/__init__.py
pyobfus/core/analyzer.py
pyobfus/core/export_detector.py
pyobfus/core/generator.py
pyobfus/core/global_table.py
pyobfus/core/orchestrator.py
pyobfus/core/parser.py
pyobfus/core/transformer.py
pyobfus/plugins/__init__.py
pyobfus/plugins/base.py
pyobfus/transformers/__init__.py
pyobfus/transformers/all_list_updater.py
pyobfus/transformers/exported_name_transformer.py
pyobfus/transformers/import_rewriter.py
pyobfus/transformers/imported_name_transformer.py
pyobfus/transformers/local_name_transformer.py
pyobfus/transformers/name_mangler.py
pyobfus/transformers/string_encoder.py
pyobfus-0.3.2.dist-info/licenses/LICENSE
pyobfus_pro/__init__.py
pyobfus_pro/anti_debug.py
pyobfus_pro/cli.py
pyobfus_pro/fingerprint.py
pyobfus_pro/license.py
pyobfus_pro/string_aes.py
pyobfus_pro/control_flow/__init__.py
pyobfus_pro/control_flow/flattener.py
pyobfus_pro/control_flow/state_machine.py
pyobfus_pro/dead_code/__init__.py
pyobfus_pro/dead_code/injector.py
pyobfus_pro/license_embed/__init__.py
pyobfus_pro/license_embed/embedder.py
pyobfus-0.3.2.dist-info/METADATA
pyobfus-0.3.2.dist-info/WHEEL
pyobfus-0.3.2.dist-info/entry_points.txt
pyobfus-0.3.2.dist-info/top_level.txt
pyobfus-0.3.2.dist-info/RECORD
