Metadata-Version: 2.4
Name: pyobfus
Version: 0.3.2
Summary: Modern Python Code Obfuscator with AST-based Transformations
Author-email: Rong Zhu <zhurong0525@gmail.com>
Maintainer-email: Rong Zhu <zhurong0525@gmail.com>
License: Apache-2.0
Project-URL: Homepage, https://github.com/zhurong2020/pyobfus
Project-URL: Documentation, https://zhurong2020.github.io/pyobfus/
Project-URL: Repository, https://github.com/zhurong2020/pyobfus
Project-URL: Source Code, https://github.com/zhurong2020/pyobfus
Project-URL: Bug Tracker, https://github.com/zhurong2020/pyobfus/issues
Project-URL: Changelog, https://github.com/zhurong2020/pyobfus/blob/main/CHANGELOG.md
Project-URL: Discussions, https://github.com/zhurong2020/pyobfus/discussions
Project-URL: Funding, https://www.buymeacoffee.com/zhurong052Q
Keywords: obfuscation,code-protection,security,python,ast,code-obfuscator,name-mangling
Classifier: Development Status :: 3 - Alpha
Classifier: Intended Audience :: Developers
Classifier: License :: OSI Approved :: Apache Software License
Classifier: Programming Language :: Python :: 3
Classifier: Programming Language :: Python :: 3.8
Classifier: Programming Language :: Python :: 3.9
Classifier: Programming Language :: Python :: 3.10
Classifier: Programming Language :: Python :: 3.11
Classifier: Programming Language :: Python :: 3.12
Classifier: Programming Language :: Python :: 3.13
Classifier: Programming Language :: Python :: 3.14
Classifier: Topic :: Software Development :: Libraries :: Python Modules
Classifier: Topic :: Security
Requires-Python: >=3.8
License-File: LICENSE
Requires-Dist: click>=8.0
Requires-Dist: pyyaml>=5.4
Requires-Dist: astunparse>=1.6.3; python_version < "3.9"
Requires-Dist: cryptography>=41.0
Provides-Extra: dev
Requires-Dist: pytest>=7.0; extra == "dev"
Requires-Dist: pytest-cov>=4.0; extra == "dev"
Requires-Dist: black>=22.0; extra == "dev"
Requires-Dist: mypy>=1.0; extra == "dev"
Requires-Dist: ruff>=0.1.0; extra == "dev"
Dynamic: license-file
